Eman/cli.py
Eman/utils.py
Eman-1.1.4.dist-info/LICENSE
Eman-1.1.4.dist-info/METADATA
Eman-1.1.4.dist-info/WHEEL
Eman-1.1.4.dist-info/entry_points.txt
Eman-1.1.4.dist-info/top_level.txt
Eman-1.1.4.dist-info/RECORD
