Metadata-Version: 2.1
Name: Eman
Version: 1.1.4
Summary: A Python package to get weather reports for any location.
Home-page: https://github.com/nikhilkumarsingh/weather-reporter
Author: eman
Author-email: eman.za1996@gmail.com
License: MIT
Platform: UNKNOWN
Classifier: License :: OSI Approved :: MIT License
Classifier: Programming Language :: Python :: 3
Classifier: Programming Language :: Python :: 3.7
Requires-Dist: requests
